[
  {
    "line": 1,
    "elements": [
      {
        "line": 3,
        "name": "",
        "description": "",
        "type": "background",
        "keyword": "Background",
        "steps": [
          {
            "result": {
              "duration": 42097800,
              "status": "passed"
            },
            "line": 4,
            "name": "User is on Retail website",
            "match": {
              "location": "stepDefinition.DesktopStepDefinition.user_is_on_retail_website()"
            },
            "keyword": "Given "
          },
          {
            "result": {
              "duration": 47384400,
              "status": "passed"
            },
            "line": 5,
            "name": "User click on Desktops tab",
            "match": {
              "location": "stepDefinition.DesktopStepDefinition.user_click_on_desktops_tab()"
            },
            "keyword": "When "
          },
          {
            "result": {
              "duration": 615504600,
              "status": "passed"
            },
            "line": 6,
            "name": "User click on Show all desktops",
            "match": {
              "location": "stepDefinition.DesktopStepDefinition.user_click_on_show_all_desktops()"
            },
            "keyword": "And "
          }
        ]
      },
      {
        "start_timestamp": "2021-11-29T20:39:45.368Z",
        "before": [
          {
            "result": {
              "duration": 3019341100,
              "status": "passed"
            },
            "match": {
              "location": "stepDefinition.Initializer.beforeHooks(io.cucumber.java.Scenario)"
            }
          }
        ],
        "line": 9,
        "name": "User verify all items are present in Desktops tab",
        "description": "",
        "id": "desktops;user-verify-all-items-are-present-in-desktops-tab",
        "after": [
          {
            "result": {
              "duration": 5140298900,
              "status": "passed"
            },
            "match": {
              "location": "stepDefinition.Initializer.afterHook(io.cucumber.java.Scenario)"
            }
          }
        ],
        "type": "scenario",
        "keyword": "Scenario",
        "steps": [
          {
            "result": {
              "duration": 170493100,
              "status": "passed"
            },
            "line": 10,
            "name": "User should see all items are present in Desktop page",
            "match": {
              "location": "stepDefinition.DesktopStepDefinition.user_should_see_all_items_are_present_in_desktop_page()"
            },
            "keyword": "Then "
          }
        ],
        "tags": [
          {
            "name": "@smokeTesting"
          }
        ]
      }
    ],
    "name": "Desktops",
    "description": "",
    "id": "desktops",
    "keyword": "Feature",
    "uri": "classpath:features/desktop.feature",
    "tags": []
  }
]